CHANGELOG.rst
LICENSE
MANIFEST.in
README.rst
numpyson.py
setup.py
test_numpyson.py
tox.ini
numpyson.egg-info/PKG-INFO
numpyson.egg-info/SOURCES.txt
numpyson.egg-info/dependency_links.txt
numpyson.egg-info/requires.txt
numpyson.egg-info/top_level.txt